rapidocr_openvino/__init__.py
rapidocr_openvino/config.yaml
rapidocr_openvino/main.py
rapidocr_openvino/cal_rec_boxes/__init__.py
rapidocr_openvino/cal_rec_boxes/main.py
rapidocr_openvino/ch_ppocr_cls/__init__.py
rapidocr_openvino/ch_ppocr_cls/text_cls.py
rapidocr_openvino/ch_ppocr_cls/utils.py
rapidocr_openvino/ch_ppocr_det/__init__.py
rapidocr_openvino/ch_ppocr_det/text_detect.py
rapidocr_openvino/ch_ppocr_det/utils.py
rapidocr_openvino/ch_ppocr_rec/__init__.py
rapidocr_openvino/ch_ppocr_rec/ppocr_keys_v1.txt
rapidocr_openvino/ch_ppocr_rec/text_recognize.py
rapidocr_openvino/ch_ppocr_rec/utils.py
rapidocr_openvino/models/ch_PP-OCRv4_det_infer.onnx
rapidocr_openvino/models/ch_PP-OCRv4_rec_infer.onnx
rapidocr_openvino/models/ch_ppocr_mobile_v2.0_cls_infer.onnx
rapidocr_openvino/utils/__init__.py
rapidocr_openvino/utils/infer_engine.py
rapidocr_openvino/utils/load_image.py
rapidocr_openvino/utils/logger.py
rapidocr_openvino/utils/parse_parameters.py
rapidocr_openvino/utils/process_img.py
rapidocr_openvino/utils/vis_res.py
rapidocr_openvino-1.4.4.dist-info/METADATA
rapidocr_openvino-1.4.4.dist-info/WHEEL
rapidocr_openvino-1.4.4.dist-info/entry_points.txt
rapidocr_openvino-1.4.4.dist-info/top_level.txt
rapidocr_openvino-1.4.4.dist-info/RECORD
